django_rq_email_backend/__init__.py
django_rq_email_backend/backends.py
django_rq_email_backend/tasks.py
django_rq_email_backend-2.0.0.dist-info/METADATA
django_rq_email_backend-2.0.0.dist-info/WHEEL
django_rq_email_backend-2.0.0.dist-info/licenses/AUTHORS.rst
django_rq_email_backend-2.0.0.dist-info/licenses/LICENSE
django_rq_email_backend-2.0.0.dist-info/RECORD
