Metadata-Version: 2.3
Name: django-rq-email-backend
Version: 2.0.0
Summary: Provides Django email integration for RQ (Redis Queue)
Project-URL: Homepage, https://github.com/knyghty/django-rq-email-backend
Project-URL: Repository, https://github.com/knyghty/django-rq-email-backend
Author-email: Tom Carrick <tom@carrick.eu>, Jeff Triplett <jeff.triplett@gmail.com>
License: Original work Copyright (c) 2013, Jeff Triplett
License-File: AUTHORS.rst
License-File: LICENSE
Classifier: Development Status :: 5 - Production/Stable
Classifier: Environment :: Web Environment
Classifier: Framework :: Django
Classifier: Framework :: Django :: 4.2
Classifier: Framework :: Django :: 5.0
Classifier: Framework :: Django :: 5.1
Classifier: Intended Audience :: Developers
Classifier: License :: OSI Approved :: BSD License
Classifier: Operating System :: OS Independent
Classifier: Programming Language :: Python
Classifier: Programming Language :: Python :: 3 :: Only
Classifier: Programming Language :: Python :: 3.8
Classifier: Programming Language :: Python :: 3.9
Classifier: Programming Language :: Python :: 3.10
Classifier: Programming Language :: Python :: 3.11
Classifier: Programming Language :: Python :: 3.12
Classifier: Topic :: Communications :: Email
Classifier: Topic :: Internet :: WWW/HTTP
Classifier: Topic :: Software Development :: Libraries :: Python Modules
Requires-Dist: django
Requires-Dist: django-rq
Requires-Dist: rq
